{ "compressionlevel":-1,
 "height":11,
 "infinite":false,
 "layers":[
        {
         "id":2,
         "image":"fase 2.png",
         "imageheight":704,
         "imagewidth":1052,
         "name":"bg",
         "offsetx":-10,
         "offsety":0,
         "opacity":1,
         "type":"imagelayer",
         "visible":true,
         "x":0,
         "y":0
        }, 
        {
         "data":[0, 0, 0, 0, 0, 0, 0, 0, 0, 0, 0, 0, 0, 0, 0, 0,
            0, 0, 0, 0, 0, 0, 0, 0, 0, 0, 0, 0, 0, 0, 0, 0,
            0, 0, 0, 0, 0, 0, 0, 0, 0, 0, 0, 0, 0, 0, 0, 0,
            0, 0, 0, 0, 0, 0, 0, 0, 0, 0, 0, 0, 0, 0, 0, 0,
            0, 0, 0, 0, 0, 0, 0, 0, 0, 0, 0, 0, 0, 0, 0, 0,
            0, 0, 0, 0, 0, 0, 0, 0, 0, 0, 0, 0, 0, 0, 0, 0,
            0, 0, 0, 0, 0, 0, 0, 0, 0, 0, 0, 0, 0, 0, 0, 0,
            0, 0, 0, 0, 0, 0, 0, 0, 0, 0, 0, 0, 0, 0, 0, 0,
            0, 0, 0, 0, 0, 0, 0, 0, 0, 0, 0, 0, 0, 0, 0, 0,
            0, 0, 0, 0, 0, 0, 0, 0, 0, 0, 0, 0, 0, 0, 0, 0,
            0, 0, 0, 0, 0, 0, 0, 0, 0, 0, 0, 0, 0, 0, 0, 0],
         "height":11,
         "id":1,
         "name":"Camada de Blocos 1",
         "opacity":1,
         "type":"tilelayer",
         "visible":false,
         "width":16,
         "x":0,
         "y":0
        }, 
        {
         "draworder":"topdown",
         "id":3,
         "name":"Objects",
         "objects":[
                {
                 "gid":1,
                 "height":64,
                 "id":10,
                 "name":"",
                 "rotation":0,
                 "type":"",
                 "visible":true,
                 "width":64,
                 "x":965.333,
                 "y":647.333
                }, 
                {
                 "height":0,
                 "id":11,
                 "name":"",
                 "polygon":[
                        {
                         "x":0,
                         "y":0
                        }, 
                        {
                         "x":18.6666666666667,
                         "y":45.3333333333334
                        }, 
                        {
                         "x":36,
                         "y":49.3333333333334
                        }, 
                        {
                         "x":22.6666666666667,
                         "y":105.333333333333
                        }, 
                        {
                         "x":62.6666666666667,
                         "y":118.666666666667
                        }, 
                        {
                         "x":36,
                         "y":158.666666666667
                        }, 
                        {
                         "x":73.3333333333334,
                         "y":182.666666666667
                        }, 
                        {
                         "x":68,
                         "y":201.333333333333
                        }, 
                        {
                         "x":105.333333333333,
                         "y":258.666666666667
                        }, 
                        {
                         "x":96,
                         "y":277.333333333333
                        }, 
                        {
                         "x":-124,
                         "y":281.333333333333
                        }, 
                        {
                         "x":-116,
                         "y":237.333333333333
                        }, 
                        {
                         "x":-94.6666666666666,
                         "y":214.666666666667
                        }, 
                        {
                         "x":-89.3333333333333,
                         "y":164
                        }, 
                        {
                         "x":-66.6666666666666,
                         "y":166.666666666667
                        }, 
                        {
                         "x":-30.6666666666666,
                         "y":29.3333333333334
                        },
                    
                        {
                         "x":-12,
                         "y":34.6666666666667
                        }],
                 "rotation":0,
                 "type":"",
                 "visible":true,
                 "width":0,
                 "x":821.333333333333,
                 "y":390.666666666667
                }, 
                {
                 "height":0,
                 "id":12,
                 "name":"",
                 "polygon":[
                        {
                         "x":0,
                         "y":0
                        }, 
                        {
                         "x":-117.333333333333,
                         "y":-4
                        }, 
                        {
                         "x":-118.666666666667,
                         "y":28
                        }, 
                        {
                         "x":1.33333333333326,
                         "y":25.3333333333334
                        }],
                 "rotation":0,
                 "type":"",
                 "visible":true,
                 "width":0,
                 "x":1040,
                 "y":649.333333333333
                }, 
                {
                 "height":0,
                 "id":13,
                 "name":"",
                 "polygon":[
                        {
                         "x":0,
                         "y":0
                        }, 
                        {
                         "x":3,
                         "y":-82
                        }, 
                        {
                         "x":28,
                         "y":-105
                        }, 
                        {
                         "x":52,
                         "y":-105
                        }, 
                        {
                         "x":63,
                         "y":-30
                        }, 
                        {
                         "x":57,
                         "y":2
                        }],
                 "rotation":0,
                 "type":"",
                 "visible":true,
                 "width":0,
                 "x":643,
                 "y":649
                }, 
                {
                 "height":0,
                 "id":14,
                 "name":"",
                 "polygon":[
                        {
                         "x":0,
                         "y":0
                        }, 
                        {
                         "x":-47,
                         "y":-78
                        }, 
                        {
                         "x":-103,
                         "y":-130
                        }, 
                        {
                         "x":-128,
                         "y":-142
                        }, 
                        {
                         "x":-166,
                         "y":-137
                        }, 
                        {
                         "x":-220,
                         "y":-107
                        }, 
                        {
                         "x":-283,
                         "y":-55
                        }, 
                        {
                         "x":-312,
                         "y":-19
                        }],
                 "rotation":0,
                 "type":"",
                 "visible":true,
                 "width":0,
                 "x":644,
                 "y":655
                }, 
                {
                 "height":0,
                 "id":15,
                 "name":"",
                 "polygon":[
                        {
                         "x":0,
                         "y":0
                        }, 
                        {
                         "x":-27.3333333333334,
                         "y":24
                        }, 
                        {
                         "x":-36.6666666666667,
                         "y":108
                        }, 
                        {
                         "x":36.6666666666666,
                         "y":112.666666666667
                        }, 
                        {
                         "x":42.6666666666666,
                         "y":78.6666666666667
                        }, 
                        {
                         "x":33.3333333333333,
                         "y":17.3333333333334
                        }, 
                        {
                         "x":19.3333333333333,
                         "y":-0.666666666666629
                        }],
                 "rotation":0,
                 "type":"",
                 "visible":true,
                 "width":0,
                 "x":294,
                 "y":525.333333333333
                }, 
                {
                 "height":0,
                 "id":16,
                 "name":"",
                 "polygon":[
                        {
                         "x":0,
                         "y":0
                        }, 
                        {
                         "x":-285,
                         "y":3.33333333333326
                        }, 
                        {
                         "x":-275,
                         "y":27.3333333333334
                        }, 
                        {
                         "x":0,
                         "y":27
                        }],
                 "rotation":0,
                 "type":"",
                 "visible":true,
                 "width":0,
                 "x":253,
                 "y":633
                }],
         "opacity":1,
         "type":"objectgroup",
         "visible":true,
         "x":0,
         "y":0
        }],
 "nextlayerid":4,
 "nextobjectid":17,
 "orientation":"orthogonal",
 "renderorder":"right-down",
 "tiledversion":"1.11.2",
 "tileheight":64,
 "tilesets":[
        {
         "columns":1,
         "firstgid":1,
         "image":"..\/mapa 1\/pinguim.png",
         "imageheight":64,
         "imagewidth":64,
         "margin":0,
         "name":"pinguim",
         "spacing":0,
         "tilecount":1,
         "tileheight":64,
         "tilewidth":64
        }],
 "tilewidth":64,
 "type":"map",
 "version":"1.10",
 "width":16
}